[
  {
    "path": "sec-fire-cables",
    "title": "Кабели для систем охранно-пожарной сигнализации",
    "category": [
      {
        "cableTitle": "Кабели для систем охранной сигнализации",
        "cableTypes": ["КСПВ", "КСПЭВ"]
      },
      {
        "cableTitle": "Не распространяющие горение при групповой прокладке",
        "cableTypes": [
          "КПСнг(А)-FRLS",
          "КПСЭнг(А)-FRLS",
          "КПСнг(А)-FRLSLTx",
          "КПСЭнг(А)-FRLSLTx",
          "КПСнг(А)-FRHF",
          "КПСЭнг(А)-FRHF"
        ]
      },
      {
        "cableTitle": "Не распространяющие горение при одиночной прокладке",
        "cableTypes": ["КПСВВ", "КПСВЭВ", "КСВВ", "КСВЭВ"]
      },
      {
        "cableTitle": "Кабели огнестойкие для групповой прокладки",
        "cableTypes": [
          "КПСВВнг(А)-LS",
          "КПСВЭВнг(А)-LS",
          "КПСВВнг(А)-LSLTx",
          "КПСВЭВнг(А)-LSLTx",
          "КСВВнг(А)-LS",
          "КСВЭВнг(А)-LS",
          "КСВВнг(А)-LSLTx",
          "КСВЭВнг(А)-LSLTx"
        ]
      }
    ]
  },
  {
    "path": "heating-cables",
    "title": "Прогревочные кабели",
    "category": [
      {
        "cableTitle": "",
        "cableTypes": ["ПНСВ"]
      }
    ]
  },
  {
    "path": "telecom-wires",
    "title": "Провода телефонные, радиотрансляционные и распределительные",
    "category": [
      {
        "cableTitle": "",
        "cableTypes": ["ПТПЖ", "ПРППМ", "ТРП", "ТРВ", "ПКСВ"]
      }
    ]
  },
  {
    "path": "cctv-cables",
    "title": "Кабели комбинированные для видеонаблюдения",
    "category": [
      {
        "cableTitle": "",
        "cableTypes": ["КВК-В-2", "КВК-П-2", "КВК-В-2нг(А)-H"]
      }
    ]
  }
]
